{
    "date": "2022-06-13 16:45:24",
    "number of frames": 100,
    "exposure_time_us": 650,
    "total_exposure_time_us": 65000,
    "user_set_FPS": 25,
    "actual_mean_FPS": 3.1781665774280285,
    "actual_final_FPS": 3.2858958989405633,
    "number of frames / actual_final_FPS": 30.43310046195984,
    "message": "70mA Laser, MS OFF, 3\" shaft_dist, 180deg amplitude, 2s period, 100ms delay, 0 ND",
    "pixels_in_hull": 45402,
    "mean": 1365.284424829717,
    "mean_err": 0.1734099750439169,
    "std": 285.04240407247266,
    "std_err": 0.18646966431784026,
    "mean/std": 4.789759015934311,
    "mean/std_err": 0.003191887811683705
}