{
    "date": "2022-06-02 14:08:30",
    "number of frames": 2000,
    "exposure_time_us": 750,
    "total_exposure_time_us": 1500000,
    "user_set_FPS": 25,
    "actual_mean_FPS": 24.90871024924076,
    "actual_final_FPS": 24.986580962432164,
    "number of frames / actual_final_FPS": 80.04296398162842,
    "message": "70mA Laser, MS ON, 7\" shaft_dist, 180deg amplitude, 2s period, 100ms delay, 0.4 ND",
    "pixels_in_hull": 26084,
    "mean": 1033.6699263916578,
    "std": 126.63316320009444,
    "mean/std": 8.162711096131623
}