{
    "date": "2022-06-02 16:10:12",
    "number of frames": 1,
    "exposure_time_us": 500,
    "total_exposure_time_us": 500,
    "user_set_FPS": 25,
    "actual_mean_FPS": 12.381014791790276,
    "actual_final_FPS": 11.656996748283817,
    "number of frames / actual_final_FPS": 0.0857853889465332,
    "message": "70mA Laser, MS OFF, 7\" shaft_dist, 180deg amplitude, 2s period, 100ms delay, 0.7 ND",
    "pixels_in_hull": 24216,
    "mean": 633.2890568219359,
    "mean_err": 0.16171480737375887,
    "std": 164.76611524994468,
    "std_err": 0.18243782991154828,
    "mean/std": 3.8435636833535685,
    "mean/std_err": 0.004367508145092102
}