{
    "date": "2022-06-02 15:31:49",
    "number of frames": 1,
    "exposure_time_us": 10,
    "total_exposure_time_us": 10,
    "user_set_FPS": 25,
    "actual_mean_FPS": 12.325494056627338,
    "actual_final_FPS": 11.885921559737021,
    "number of frames / actual_final_FPS": 0.08413314819335938,
    "message": "70mA Laser, MS OFF, 7\" shaft_dist, 180deg amplitude, 2s period, 100ms delay, 1.8 ND",
    "pixels_in_hull": 24236,
    "mean": 837.166793200198,
    "mean_err": 0.18585554585416125,
    "std": 215.93167675075404,
    "std_err": 0.20426635255581602,
    "mean/std": 3.8769985293381675,
    "mean/std_err": 0.003767194837669788
}