{
    "date": "2022-06-02 15:49:28",
    "number of frames": 1,
    "exposure_time_us": 100,
    "total_exposure_time_us": 100,
    "user_set_FPS": 25,
    "actual_mean_FPS": 12.4986709577448,
    "actual_final_FPS": 11.903732631005358,
    "number of frames / actual_final_FPS": 0.08400726318359375,
    "message": "70mA Laser, MS ON, 7\" shaft_dist, 180deg amplitude, 2s period, 100ms delay, 0 ND",
    "pixels_in_hull": 24192,
    "mean": 664.6340691137566,
    "mean_err": 0.16575071587946982,
    "std": 167.2694669045774,
    "std_err": 0.17993420647863156,
    "mean/std": 3.973433295467558,
    "mean/std_err": 0.004387641069994804
}