{
    "date": "2022-06-02 16:09:40",
    "number of frames": 1,
    "exposure_time_us": 500,
    "total_exposure_time_us": 500,
    "user_set_FPS": 25,
    "actual_mean_FPS": 12.431066522428535,
    "actual_final_FPS": 12.129557653155654,
    "number of frames / actual_final_FPS": 0.0824432373046875,
    "message": "70mA Laser, MS OFF, 7\" shaft_dist, 180deg amplitude, 2s period, 100ms delay, 0.7 ND",
    "pixels_in_hull": 24235,
    "mean": 632.826094491438,
    "mean_err": 0.161592305572374,
    "std": 163.00871676698625,
    "std_err": 0.17960845121514765,
    "mean/std": 3.882161071153237,
    "mean/std_err": 0.0043908608342633
}